inkBoarddesigner/__init__.py
inkBoarddesigner/const.py
inkBoarddesigner/integrationloader.py
inkBoarddesigner/runners.py
inkBoarddesigner/settings.py
inkBoarddesigner/util.py
inkBoarddesigner/emulator/__init__.py
inkBoarddesigner/emulator/const.py
inkBoarddesigner/emulator/device.py
inkBoarddesigner/emulator/pssm_functions.py
inkBoarddesigner/files/background_alpha.png
inkBoarddesigner/files/background_alpha_dark.png
inkBoarddesigner/files/background_alpha_light.png
inkBoarddesigner/files/inkboard_designer_icon.ico
inkBoarddesigner/integrations/__init__.py
inkBoarddesigner/integrations/homeassistant_client/HAelements.py
inkBoarddesigner/integrations/homeassistant_client/__init__.py
inkBoarddesigner/integrations/homeassistant_client/client.py
inkBoarddesigner/integrations/homeassistant_client/clientelements.py
inkBoarddesigner/integrations/homeassistant_client/constants.py
inkBoarddesigner/integrations/homeassistant_client/helpers.py
inkBoarddesigner/integrations/homeassistant_client/home-assistant.png
inkBoarddesigner/integrations/homeassistant_client/icon_sets.py
inkBoarddesigner/integrations/homeassistant_client/manifest.json
inkBoarddesigner/integrations/homeassistant_client/parser.py
inkBoarddesigner/integrations/homeassistant_client/trigger_functions.py
inkBoarddesigner/integrations/homeassistant_client/designer/__init__.py
inkBoarddesigner/integrations/homeassistant_client/designer/const.py
inkBoarddesigner/integrations/meteocons/__init__.py
inkBoarddesigner/integrations/meteocons/manifest.json
inkBoarddesigner/integrations/meteocons/icons/meteocons/LICENSE
inkBoarddesigner/integrations/meteocons/icons/meteocons/package.json
inkBoarddesigner/integrations/meteocons/icons/meteocons/filled/barometer.png
inkBoarddesigner/integrations/meteocons/icons/meteocons/filled/clear-day.png
inkBoarddesigner/integrations/meteocons/icons/meteocons/filled/clear-night.png
inkBoarddesigner/integrations/meteocons/icons/meteocons/filled/cloudy.png
inkBoarddesigner-0.3.0.dist-info/LICENSE
inkBoarddesigner-0.3.0.dist-info/METADATA
inkBoarddesigner-0.3.0.dist-info/WHEEL
inkBoarddesigner-0.3.0.dist-info/top_level.txt
inkBoarddesigner-0.3.0.dist-info/RECORD
