Metadata-Version: 2.2
Name: inkBoarddesigner
Version: 0.3.0
Summary: inkBoard designer bridges the gaps between designing an inkBoard dashboard and deploying it to a platform, without being tied down by the platform's limitations.
Author: Slalamander
License:                     GNU GENERAL PUBLIC LICENSE
Project-URL: Homepage, https://github.com/Slalamander/inkBoarddesigner
Project-URL: source, https://github.com/Slalamander/inkBoarddesigner
Keywords: gui,pixels,interface,MaterialDesignIcon,mdi icons,dashboards,dashboarding
Classifier: Programming Language :: Python :: 3.9
Classifier: Programming Language :: Python :: 3.10
Classifier: Operating System :: OS Independent
Classifier: License :: OSI Approved :: GNU General Public License v3 (GPLv3)
Requires-Python: >=3.9
License-File: LICENSE
Requires-Dist: inkBoard>=0.2.6
Requires-Dist: ttkbootstrap
Requires-Dist: tkthread
Requires-Dist: packaging
